MANIFEST.in
Pipfile
Pipfile.lock
README.md
data/stats.md
data/stats.txt
dumps/catMap.p
dumps/category.json
dumps/trie.p
openfalcon.egg-info/PKG-INFO
openfalcon.egg-info/SOURCES.txt
openfalcon.egg-info/dependency_links.txt
openfalcon.egg-info/entry_points.txt
openfalcon.egg-info/requires.txt
openfalcon.egg-info/top_level.txt
services/__init__.py
services/category.py
services/code.py
services/getSearchResults.py
services/index.py
services/openfalcon.py
services/recommendationUtils.py
services/recommendations.py
services/search.py
services/stats.py
services/trie.py
openfalcon-0.0.1.dist-info/LICENSE
openfalcon-0.0.1.dist-info/METADATA
openfalcon-0.0.1.dist-info/WHEEL
openfalcon-0.0.1.dist-info/entry_points.txt
openfalcon-0.0.1.dist-info/top_level.txt
openfalcon-0.0.1.dist-info/RECORD
